qronos_django/__init__.py
qronos_django/admin.py
qronos_django/apps.py
qronos_django/connection.py
qronos_django/imports.py
qronos_django/models.py
qronos_django/settings.py
qronos_django/tasks.py
qronos_django/migrations/0001_initial.py
qronos_django/migrations/0002_auto_20201102_0813.py
qronos_django/migrations/0003_auto_20220124_1047.py
qronos_django/migrations/__init__.py
qronos_django-1.2.1.dist-info/LICENSE
qronos_django-1.2.1.dist-info/METADATA
qronos_django-1.2.1.dist-info/WHEEL
qronos_django-1.2.1.dist-info/top_level.txt
qronos_django-1.2.1.dist-info/RECORD
