Metadata-Version: 2.1
Name: qronos-django
Version: 1.2.1
Summary: Django package for using the QRonos Python Client
Home-page: https://github.com/QuickRelease/qronos-django.git
Author: Nick Solly
Author-email: nick.solly@quickrelease.co.uk
License: All Rights Reserved
Classifier: Environment :: Web Environment
Classifier: Framework :: Django
Classifier: Intended Audience :: Developers
Classifier: Operating System :: OS Independent
Classifier: Programming Language :: Python
Classifier: Programming Language :: Python :: 3
Classifier: Programming Language :: Python :: 3 :: Only
Classifier: Programming Language :: Python :: 3.6
Classifier: Programming Language :: Python :: 3.7
Classifier: Programming Language :: Python :: 3.8
Classifier: Topic :: Internet :: WWW/HTTP
Classifier: Topic :: Internet :: WWW/HTTP :: Dynamic Content
License-File: LICENSE
Requires-Dist: qronos-client >=1.7.0
Requires-Dist: Django >=4.2
Requires-Dist: celery >=4.4.0
